{"ORD_REQUEST_ID":"15cd7d38-36e2-403f-a564-4e908e110fbb","caller":"VLOCITY","orderno":"00022582","ordernotes":"","orderid":"8013N000003rtmOQAQ","AccountNo":"13601539","BillAccountNumber":"16161616","orderOffers":[{"ORDER_LINE_NRC_WAIVER_REASON":"testing1","ORDER_LINE_UOM":"","ORDER_LINE_PRODUCT_CODE":"","ORDER_LINE_COMPONENT_QTY":"1","ORDER_LINE_AMOUNT":"","ORDER_LINE_SUB_TYPE":"Recurring","ORDER_LINE_PROMOTION_PERIOD":"","ORDER_LINE_TYPE":"C","ORDER_LINE_COMPONENT_CODE":"","ORDER_LINE_SPECIAL_DISCOUNT_CODE":"","ORDER_LINE_PRODUCT_QTY":"1","ORDER_LINE_ITEM":"8023N000003gIVPQA2","ORDER_LINE_PACKAGE_CODE":"","ORDER_LINE_PLAN_CODE":"","ORDER_LINE_ACTION":"ON","ORDER_LINE_PROMOTION_UOM":"","ORDER_LINE_PROMO_ORDERNO":"testing"},{"ORDER_LINE_NRC_WAIVER_REASON":"testing4","ORDER_LINE_UOM":"","ORDER_LINE_PRODUCT_CODE":"b.B.4782","ORDER_LINE_COMPONENT_QTY":"1","ORDER_LINE_AMOUNT":"0","ORDER_LINE_SUB_TYPE":"Recurring","ORDER_LINE_PROMOTION_PERIOD":"","ORDER_LINE_TYPE":"C","ORDER_LINE_COMPONENT_CODE":"","ORDER_LINE_SPECIAL_DISCOUNT_CODE":"","ORDER_LINE_PRODUCT_QTY":"1","ORDER_LINE_ITEM":"8023N000003gIVQQA2","ORDER_LINE_PACKAGE_CODE":"","ORDER_LINE_PLAN_CODE":"","ORDER_LINE_ACTION":"ON","ORDER_LINE_PROMOTION_UOM":"","ORDER_LINE_PROMO_ORDERNO":"testing3"},{"ORDER_LINE_NRC_WAIVER_REASON":"","ORDER_LINE_UOM":"","ORDER_LINE_PRODUCT_CODE":"","ORDER_LINE_COMPONENT_QTY":"1","ORDER_LINE_AMOUNT":"0","ORDER_LINE_SUB_TYPE":"Recurring","ORDER_LINE_PROMOTION_PERIOD":"","ORDER_LINE_TYPE":"C","ORDER_LINE_COMPONENT_CODE":"","ORDER_LINE_SPECIAL_DISCOUNT_CODE":"","ORDER_LINE_PRODUCT_QTY":"1","ORDER_LINE_ITEM":"8023N000003gIVRQA2","ORDER_LINE_PACKAGE_CODE":"","ORDER_LINE_PLAN_CODE":"","ORDER_LINE_ACTION":"ON","ORDER_LINE_PROMOTION_UOM":"","ORDER_LINE_PROMO_ORDERNO":""},{"ORDER_LINE_NRC_WAIVER_REASON":"","ORDER_LINE_UOM":"","ORDER_LINE_PRODUCT_CODE":"","ORDER_LINE_COMPONENT_QTY":"1","ORDER_LINE_AMOUNT":"0","ORDER_LINE_SUB_TYPE":"One-time","ORDER_LINE_PROMOTION_PERIOD":"","ORDER_LINE_TYPE":"C","ORDER_LINE_COMPONENT_CODE":"","ORDER_LINE_SPECIAL_DISCOUNT_CODE":"","ORDER_LINE_PRODUCT_QTY":"1","ORDER_LINE_ITEM":"8023N000003gIVTQA2","ORDER_LINE_PACKAGE_CODE":"","ORDER_LINE_PLAN_CODE":"","ORDER_LINE_ACTION":"ON","ORDER_LINE_PROMOTION_UOM":"","ORDER_LINE_PROMO_ORDERNO":""}],"orderdetails":[{"value":"Telco","key":"ORD_ORDEREDSERVICE"},{"value":"","key":"ORD_ORDEREDSERVICETYPE"},{"value":"","key":"ORD_ORDEREDSERVICETYPE"}],"serviceno":"DSLS3000152","orderdate":"04/04/2022 11:54:48"}